{
  "cisa_alerts": {
    "consecutive_ok": 1,
    "consecutive_fail": 0,
    "total_ok": 63,
    "total_calls": 311,
    "last_ok": "2026-07-09T22:40:02.721493+00:00",
    "last_fail": "2026-07-09T12:13:00.006973+00:00"
  },
  "cisa_kev": {
    "consecutive_ok": 0,
    "consecutive_fail": 5,
    "total_ok": 140,
    "total_calls": 311,
    "last_ok": "2026-07-08T10:28:25.956966+00:00",
    "last_fail": "2026-07-09T22:40:02.721419+00:00"
  },
  "bleepingcomputer": {
    "consecutive_ok": 11,
    "consecutive_fail": 0,
    "total_ok": 271,
    "total_calls": 311,
    "last_ok": "2026-07-09T22:40:01.717416+00:00",
    "last_fail": "2026-07-06T09:07:12.899482+00:00"
  },
  "krebs": {
    "consecutive_ok": 0,
    "consecutive_fail": 2,
    "total_ok": 33,
    "total_calls": 311,
    "last_ok": "2026-07-08T23:19:02.939032+00:00",
    "last_fail": "2026-07-09T22:40:02.401844+00:00"
  },
  "thehackernews": {
    "consecutive_ok": 12,
    "consecutive_fail": 0,
    "total_ok": 261,
    "total_calls": 311,
    "last_ok": "2026-07-09T22:40:02.176606+00:00",
    "last_fail": "2026-07-05T23:12:01.103864+00:00"
  },
  "gh_security_blog": {
    "consecutive_ok": 1,
    "consecutive_fail": 0,
    "total_ok": 12,
    "total_calls": 311,
    "last_ok": "2026-07-09T22:40:01.809544+00:00",
    "last_fail": "2026-07-09T12:13:00.077525+00:00"
  },
  "github_changelog": {
    "consecutive_ok": 1,
    "consecutive_fail": 0,
    "total_ok": 175,
    "total_calls": 311,
    "last_ok": "2026-07-09T22:40:02.676344+00:00",
    "last_fail": "2026-07-09T12:13:00.148120+00:00"
  },
  "ncsc_uk": {
    "consecutive_ok": 0,
    "consecutive_fail": 311,
    "total_ok": 0,
    "total_calls": 311,
    "last_ok": null,
    "last_fail": "2026-07-09T22:40:02.401876+00:00"
  },
  "cloudflare_blog": {
    "consecutive_ok": 1,
    "consecutive_fail": 0,
    "total_ok": 108,
    "total_calls": 311,
    "last_ok": "2026-07-09T22:40:03.205426+00:00",
    "last_fail": "2026-07-09T12:13:01.147898+00:00"
  },
  "snyk_blog": {
    "consecutive_ok": 0,
    "consecutive_fail": 52,
    "total_ok": 24,
    "total_calls": 311,
    "last_ok": "2026-06-24T23:16:37.117755+00:00",
    "last_fail": "2026-07-09T22:40:05.950831+00:00"
  },
  "bsi_germany": {
    "consecutive_ok": 6,
    "consecutive_fail": 0,
    "total_ok": 190,
    "total_calls": 311,
    "last_ok": "2026-07-09T22:40:04.068144+00:00",
    "last_fail": "2026-07-08T00:07:58.789225+00:00"
  },
  "gcp_security": {
    "consecutive_ok": 0,
    "consecutive_fail": 8,
    "total_ok": 27,
    "total_calls": 311,
    "last_ok": "2026-07-07T12:06:35.995383+00:00",
    "last_fail": "2026-07-09T22:40:03.240719+00:00"
  },
  "cyberscoop": {
    "consecutive_ok": 1,
    "consecutive_fail": 0,
    "total_ok": 187,
    "total_calls": 311,
    "last_ok": "2026-07-09T22:40:03.532500+00:00",
    "last_fail": "2026-07-09T12:13:01.214502+00:00"
  },
  "securityweek": {
    "consecutive_ok": 5,
    "consecutive_fail": 0,
    "total_ok": 250,
    "total_calls": 311,
    "last_ok": "2026-07-09T22:40:03.055013+00:00",
    "last_fail": "2026-07-08T10:28:26.342565+00:00"
  },
  "darkreading": {
    "consecutive_ok": 8,
    "consecutive_fail": 0,
    "total_ok": 233,
    "total_calls": 311,
    "last_ok": "2026-07-09T22:40:04.148129+00:00",
    "last_fail": "2026-07-07T12:06:35.995421+00:00"
  },
  "therecord": {
    "consecutive_ok": 1,
    "consecutive_fail": 0,
    "total_ok": 161,
    "total_calls": 311,
    "last_ok": "2026-07-09T22:40:03.448699+00:00",
    "last_fail": "2026-07-09T12:13:01.341421+00:00"
  },
  "talos_blog": {
    "consecutive_ok": 1,
    "consecutive_fail": 0,
    "total_ok": 37,
    "total_calls": 311,
    "last_ok": "2026-07-09T22:40:04.937945+00:00",
    "last_fail": "2026-07-09T12:13:01.335964+00:00"
  },
  "unit42": {
    "consecutive_ok": 0,
    "consecutive_fail": 6,
    "total_ok": 87,
    "total_calls": 311,
    "last_ok": "2026-07-08T00:07:58.826223+00:00",
    "last_fail": "2026-07-09T22:40:03.803525+00:00"
  },
  "portswigger_daily": {
    "consecutive_ok": 0,
    "consecutive_fail": 112,
    "total_ok": 0,
    "total_calls": 112,
    "last_ok": null,
    "last_fail": "2026-05-08T19:11:04.347932+00:00"
  },
  "ms_security_blog": {
    "consecutive_ok": 1,
    "consecutive_fail": 0,
    "total_ok": 120,
    "total_calls": 311,
    "last_ok": "2026-07-09T22:40:05.957974+00:00",
    "last_fail": "2026-07-09T12:13:01.470973+00:00"
  },
  "malwarebytes_blog": {
    "consecutive_ok": 1,
    "consecutive_fail": 0,
    "total_ok": 73,
    "total_calls": 112,
    "last_ok": "2026-05-08T19:11:04.411870+00:00",
    "last_fail": "2026-05-08T10:45:20.348571+00:00"
  },
  "aws_security_blog": {
    "consecutive_ok": 0,
    "consecutive_fail": 2,
    "total_ok": 99,
    "total_calls": 311,
    "last_ok": "2026-07-08T23:19:04.337953+00:00",
    "last_fail": "2026-07-09T22:40:05.957944+00:00"
  },
  "nvd": {
    "consecutive_ok": 24,
    "consecutive_fail": 0,
    "total_ok": 280,
    "total_calls": 309,
    "last_ok": "2026-07-09T22:40:14.985008+00:00",
    "last_fail": "2026-07-02T12:17:29.598872+00:00"
  },
  "acsc_australia": {
    "consecutive_ok": 0,
    "consecutive_fail": 112,
    "total_ok": 0,
    "total_calls": 112,
    "last_ok": null,
    "last_fail": "2026-05-08T19:11:18.095372+00:00"
  },
  "projectdiscovery": {
    "consecutive_ok": 0,
    "consecutive_fail": 72,
    "total_ok": 10,
    "total_calls": 199,
    "last_ok": "2026-06-18T23:55:09.964995+00:00",
    "last_fail": "2026-07-09T22:40:06.309390+00:00"
  },
  "aws_security_bulletins": {
    "consecutive_ok": 0,
    "consecutive_fail": 6,
    "total_ok": 43,
    "total_calls": 199,
    "last_ok": "2026-07-08T00:07:59.589443+00:00",
    "last_fail": "2026-07-09T22:40:06.416442+00:00"
  },
  "trail_of_bits": {
    "consecutive_ok": 0,
    "consecutive_fail": 3,
    "total_ok": 14,
    "total_calls": 199,
    "last_ok": "2026-07-08T21:19:04.742281+00:00",
    "last_fail": "2026-07-09T22:40:06.883571+00:00"
  },
  "msrc_update_guide": {
    "consecutive_ok": 0,
    "consecutive_fail": 1,
    "total_ok": 127,
    "total_calls": 199,
    "last_ok": "2026-07-09T12:13:03.810501+00:00",
    "last_fail": "2026-07-09T22:40:10.212253+00:00"
  },
  "project_zero": {
    "consecutive_ok": 0,
    "consecutive_fail": 199,
    "total_ok": 0,
    "total_calls": 199,
    "last_ok": null,
    "last_fail": "2026-07-09T22:40:13.605790+00:00"
  }
}